Metadata-Version: 1.0
Name: mt-distributions
Version: 0.2
Summary: Gaussian and Binomial distributions, made for the Udacity Machine Learning Foundations course
Home-page: UNKNOWN
Author: UNKNOWN
Author-email: UNKNOWN
License: UNKNOWN
Platform: UNKNOWN
